geothmetic_meandian/__init__.py
geothmetic_meandian/geometric_mean.py
py-geothmetic-meandian/__init__.py
py_geothmetic_meandian/__init__.py
py_geothmetic_meandian/geometric_mean.py
geothmetic_meandian-0.1.4.dist-info/LICENSE
geothmetic_meandian-0.1.4.dist-info/METADATA
geothmetic_meandian-0.1.4.dist-info/WHEEL
geothmetic_meandian-0.1.4.dist-info/top_level.txt
geothmetic_meandian-0.1.4.dist-info/RECORD
