Metadata-Version: 2.1
Name: geothmetic-meandian
Version: 0.1.4
Summary: A python implementation of the "Geothmetic Meandian" as proposed in XKCD #2435
Home-page: https://github.com/mdelcambre/py-geothmetic-meandian
Author: Mark Delcambre
Author-email: mark@charkbot.com
License: UNKNOWN
Project-URL: Bug Tracker, https://github.com/mdelcambre/py-geothmetic-meandian/issues
Platform: UNKNOWN
Classifier: Programming Language :: Python :: 3
Classifier: License :: OSI Approved :: Apache Software License
Classifier: Operating System :: OS Independent
Requires-Python: >=3.6
